{
  "genesis": {
    "name": "Génesis",
    "chapters": 50,
    "testament": "old",
    "order": 1
  },
  "exodo": {
    "name": "Éxodo",
    "chapters": 40,
    "testament": "old",
    "order": 2
  },
  "levitico": {
    "name": "Levítico",
    "chapters": 27,
    "testament": "old",
    "order": 3
  },
  "numeros": {
    "name": "Números",
    "chapters": 36,
    "testament": "old",
    "order": 4
  },
  "deuteronomio": {
    "name": "Deuteronomio",
    "chapters": 34,
    "testament": "old",
    "order": 5
  },
  "josue": {
    "name": "Josué",
    "chapters": 24,
    "testament": "old",
    "order": 6
  },
  "jueces": {
    "name": "Jueces",
    "chapters": 21,
    "testament": "old",
    "order": 7
  },
  "rut": {
    "name": "Rut",
    "chapters": 4,
    "testament": "old",
    "order": 8
  },
  "1-samuel": {
    "name": "1 Samuel",
    "chapters": 31,
    "testament": "old",
    "order": 9
  },
  "2-samuel": {
    "name": "2 Samuel",
    "chapters": 24,
    "testament": "old",
    "order": 10
  },
  "1-reyes": {
    "name": "1 Reyes",
    "chapters": 22,
    "testament": "old",
    "order": 11
  },
  "2-reyes": {
    "name": "2 Reyes",
    "chapters": 25,
    "testament": "old",
    "order": 12
  },
  "1-cronicas": {
    "name": "1 Crónicas",
    "chapters": 29,
    "testament": "old",
    "order": 13
  },
  "2-cronicas": {
    "name": "2 Crónicas",
    "chapters": 36,
    "testament": "old",
    "order": 14
  },
  "esdras": {
    "name": "Esdras",
    "chapters": 10,
    "testament": "old",
    "order": 15
  },
  "nehemias": {
    "name": "Nehemías",
    "chapters": 13,
    "testament": "old",
    "order": 16
  },
  "ester": {
    "name": "Ester",
    "chapters": 10,
    "testament": "old",
    "order": 17
  },
  "job": {
    "name": "Job",
    "chapters": 42,
    "testament": "old",
    "order": 18
  },
  "salmos": {
    "name": "Salmos",
    "chapters": 150,
    "testament": "old",
    "order": 19
  },
  "proverbios": {
    "name": "Proverbios",
    "chapters": 31,
    "testament": "old",
    "order": 20
  },
  "eclesiastes": {
    "name": "Eclesiastés",
    "chapters": 12,
    "testament": "old",
    "order": 21
  },
  "cantares": {
    "name": "Cantares",
    "chapters": 8,
    "testament": "old",
    "order": 22
  },
  "isaias": {
    "name": "Isaías",
    "chapters": 66,
    "testament": "old",
    "order": 23
  },
  "jeremias": {
    "name": "Jeremías",
    "chapters": 52,
    "testament": "old",
    "order": 24
  },
  "lamentaciones": {
    "name": "Lamentaciones",
    "chapters": 5,
    "testament": "old",
    "order": 25
  },
  "ezequiel": {
    "name": "Ezequiel",
    "chapters": 48,
    "testament": "old",
    "order": 26
  },
  "daniel": {
    "name": "Daniel",
    "chapters": 12,
    "testament": "old",
    "order": 27
  },
  "oseas": {
    "name": "Oseas",
    "chapters": 14,
    "testament": "old",
    "order": 28
  },
  "joel": {
    "name": "Joel",
    "chapters": 3,
    "testament": "old",
    "order": 29
  },
  "amos": {
    "name": "Amós",
    "chapters": 9,
    "testament": "old",
    "order": 30
  },
  "abdias": {
    "name": "Abdías",
    "chapters": 1,
    "testament": "old",
    "order": 31
  },
  "jonas": {
    "name": "Jonás",
    "chapters": 4,
    "testament": "old",
    "order": 32
  },
  "miqueas": {
    "name": "Miqueas",
    "chapters": 7,
    "testament": "old",
    "order": 33
  },
  "nahum": {
    "name": "Nahúm",
    "chapters": 3,
    "testament": "old",
    "order": 34
  },
  "habacuc": {
    "name": "Habacuc",
    "chapters": 3,
    "testament": "old",
    "order": 35
  },
  "sofonias": {
    "name": "Sofonías",
    "chapters": 3,
    "testament": "old",
    "order": 36
  },
  "hageo": {
    "name": "Hageo",
    "chapters": 2,
    "testament": "old",
    "order": 37
  },
  "zacarias": {
    "name": "Zacarías",
    "chapters": 14,
    "testament": "old",
    "order": 38
  },
  "malaquias": {
    "name": "Malaquías",
    "chapters": 4,
    "testament": "old",
    "order": 39
  },
  "mateo": {
    "name": "Mateo",
    "chapters": 28,
    "testament": "new",
    "order": 40
  },
  "marcos": {
    "name": "Marcos",
    "chapters": 16,
    "testament": "new",
    "order": 41
  },
  "lucas": {
    "name": "Lucas",
    "chapters": 24,
    "testament": "new",
    "order": 42
  },
  "juan": {
    "name": "Juan",
    "chapters": 21,
    "testament": "new",
    "order": 43
  },
  "hechos": {
    "name": "Hechos",
    "chapters": 28,
    "testament": "new",
    "order": 44
  },
  "romanos": {
    "name": "Romanos",
    "chapters": 16,
    "testament": "new",
    "order": 45
  },
  "1-corintios": {
    "name": "1 Corintios",
    "chapters": 16,
    "testament": "new",
    "order": 46
  },
  "2-corintios": {
    "name": "2 Corintios",
    "chapters": 13,
    "testament": "new",
    "order": 47
  },
  "galatas": {
    "name": "Gálatas",
    "chapters": 6,
    "testament": "new",
    "order": 48
  },
  "efesios": {
    "name": "Efesios",
    "chapters": 6,
    "testament": "new",
    "order": 49
  },
  "filipenses": {
    "name": "Filipenses",
    "chapters": 4,
    "testament": "new",
    "order": 50
  },
  "colosenses": {
    "name": "Colosenses",
    "chapters": 4,
    "testament": "new",
    "order": 51
  },
  "1-tesalonicenses": {
    "name": "1 Tesalonicenses",
    "chapters": 5,
    "testament": "new",
    "order": 52
  },
  "2-tesalonicenses": {
    "name": "2 Tesalonicenses",
    "chapters": 3,
    "testament": "new",
    "order": 53
  },
  "1-timoteo": {
    "name": "1 Timoteo",
    "chapters": 6,
    "testament": "new",
    "order": 54
  },
  "2-timoteo": {
    "name": "2 Timoteo",
    "chapters": 4,
    "testament": "new",
    "order": 55
  },
  "tito": {
    "name": "Tito",
    "chapters": 3,
    "testament": "new",
    "order": 56
  },
  "filemon": {
    "name": "Filemón",
    "chapters": 1,
    "testament": "new",
    "order": 57
  },
  "hebreos": {
    "name": "Hebreos",
    "chapters": 13,
    "testament": "new",
    "order": 58
  },
  "santiago": {
    "name": "Santiago",
    "chapters": 5,
    "testament": "new",
    "order": 59
  },
  "1-pedro": {
    "name": "1 Pedro",
    "chapters": 5,
    "testament": "new",
    "order": 60
  },
  "2-pedro": {
    "name": "2 Pedro",
    "chapters": 3,
    "testament": "new",
    "order": 61
  },
  "1-juan": {
    "name": "1 Juan",
    "chapters": 5,
    "testament": "new",
    "order": 62
  },
  "2-juan": {
    "name": "2 Juan",
    "chapters": 1,
    "testament": "new",
    "order": 63
  },
  "3-juan": {
    "name": "3 Juan",
    "chapters": 1,
    "testament": "new",
    "order": 64
  },
  "judas": {
    "name": "Judas",
    "chapters": 1,
    "testament": "new",
    "order": 65
  },
  "apocalipsis": {
    "name": "Apocalipsis",
    "chapters": 22,
    "testament": "new",
    "order": 66
  }
}